odoo/addons/excel_import_export/README.rst
odoo/addons/excel_import_export/__init__.py
odoo/addons/excel_import_export/__manifest__.py
odoo/addons/excel_import_export/controllers/__init__.py
odoo/addons/excel_import_export/controllers/main.py
odoo/addons/excel_import_export/i18n/excel_import_export.pot
odoo/addons/excel_import_export/i18n/it.po
odoo/addons/excel_import_export/i18n/tr.po
odoo/addons/excel_import_export/i18n/zh_CN.po
odoo/addons/excel_import_export/models/__init__.py
odoo/addons/excel_import_export/models/common.py
odoo/addons/excel_import_export/models/ir_report.py
odoo/addons/excel_import_export/models/styles.py
odoo/addons/excel_import_export/models/xlsx_export.py
odoo/addons/excel_import_export/models/xlsx_import.py
odoo/addons/excel_import_export/models/xlsx_report.py
odoo/addons/excel_import_export/models/xlsx_template.py
odoo/addons/excel_import_export/readme/CONTRIBUTORS.rst
odoo/addons/excel_import_export/readme/DESCRIPTION.rst
odoo/addons/excel_import_export/readme/HISTORY.rst
odoo/addons/excel_import_export/readme/INSTALL.rst
odoo/addons/excel_import_export/readme/ROADMAP.rst
odoo/addons/excel_import_export/readme/USAGE.rst
odoo/addons/excel_import_export/security/ir.model.access.csv
odoo/addons/excel_import_export/static/description/icon.png
odoo/addons/excel_import_export/static/description/index.html
odoo/addons/excel_import_export/static/src/js/report/action_manager_report.js
odoo/addons/excel_import_export/views/webclient_templates.xml
odoo/addons/excel_import_export/views/xlsx_report.xml
odoo/addons/excel_import_export/views/xlsx_template_view.xml
odoo/addons/excel_import_export/wizard/__init__.py
odoo/addons/excel_import_export/wizard/export_xlsx_wizard.py
odoo/addons/excel_import_export/wizard/export_xlsx_wizard.xml
odoo/addons/excel_import_export/wizard/import_xlsx_wizard.py
odoo/addons/excel_import_export/wizard/import_xlsx_wizard.xml
odoo12_addon_excel_import_export-12.0.1.0.8.dist-info/METADATA
odoo12_addon_excel_import_export-12.0.1.0.8.dist-info/WHEEL
odoo12_addon_excel_import_export-12.0.1.0.8.dist-info/top_level.txt
odoo12_addon_excel_import_export-12.0.1.0.8.dist-info/RECORD
