Metadata-Version: 2.1
Name: odoo12-addon-excel-import-export
Version: 12.0.1.0.8
Summary: Base module for developing Excel import/export/report
Home-page: https://github.com/OCA/server-tools
Author: Ecosoft,Odoo Community Association (OCA)
Author-email: support@odoo-community.org
License: AGPL-3
Platform: UNKNOWN
Classifier: Programming Language :: Python
Classifier: Framework :: Odoo
Classifier: Framework :: Odoo :: 12.0
Classifier: License :: OSI Approved :: GNU Affero General Public License v3
Classifier: Development Status :: 4 - Beta
Requires-Python: >=3.5
Requires-Dist: odoo <12.1dev,>=12.0a
Requires-Dist: openpyxl
Requires-Dist: xlrd
Requires-Dist: xlwt
